ws735Service/__init__.py
ws735Service/__main__.py
ws735Service/const.py
ws735Service/service.py
pih_ws735-0.11.dist-info/METADATA
pih_ws735-0.11.dist-info/WHEEL
pih_ws735-0.11.dist-info/entry_points.txt
pih_ws735-0.11.dist-info/top_level.txt
pih_ws735-0.11.dist-info/RECORD
