Metadata-Version: 2.1
Name: pih-ws735
Version: 0.11
Summary: PIH ws-735 service package
Home-page: https://pacifichosp.com/
Author: Nikita Karachentsev
Author-email: it@pacifichosp.com
License: MIT
Requires-Dist: ipih
Requires-Dist: pywin32
Requires-Dist: Pillow
